MANIFEST.in
README.rst
VERSION
requirements.txt
setup.py
src/json_sort/__init__.py
src/json_sort/lib.py
src/json_sort/scripts.py
src/json_sort.egg-info/PKG-INFO
src/json_sort.egg-info/SOURCES.txt
src/json_sort.egg-info/dependency_links.txt
src/json_sort.egg-info/entry_points.txt
src/json_sort.egg-info/requires.txt
src/json_sort.egg-info/top_level.txt
src/json_sort.egg-info/zip-safe