Metadata-Version: 1.1
Name: json-sort
Version: 0.1.2
Summary: Just a tiny tool to sort keys in a json file
Home-page: https://github.com/cdumay/json-sort
Author: Cedric DUMAY
Author-email: cedric.dumay@gmail.com
License: Apache License
Platform: UNKNOWN
Classifier: Programming Language :: Python
